trytond/modules/health_stock_surgery/COPYING
trytond/modules/health_stock_surgery/README.rst
trytond/modules/health_stock_surgery/__init__.py
trytond/modules/health_stock_surgery/data/messages/messages.xml
trytond/modules/health_stock_surgery/exceptions.py
trytond/modules/health_stock_surgery/health_stock_surgery.py
trytond/modules/health_stock_surgery/health_stock_surgery_view.xml
trytond/modules/health_stock_surgery/locale/ar.po
trytond/modules/health_stock_surgery/locale/de.po
trytond/modules/health_stock_surgery/locale/el.po
trytond/modules/health_stock_surgery/locale/eo.po
trytond/modules/health_stock_surgery/locale/es.po
trytond/modules/health_stock_surgery/locale/fr.po
trytond/modules/health_stock_surgery/locale/health_stock_surgery.pot
trytond/modules/health_stock_surgery/locale/it_IT.po
trytond/modules/health_stock_surgery/locale/ja_JP.po
trytond/modules/health_stock_surgery/locale/ka.po
trytond/modules/health_stock_surgery/locale/lo.po
trytond/modules/health_stock_surgery/locale/pt_BR.po
trytond/modules/health_stock_surgery/locale/sv.po
trytond/modules/health_stock_surgery/locale/tr.po
trytond/modules/health_stock_surgery/locale/uk.po
trytond/modules/health_stock_surgery/locale/zh_CN.po
trytond/modules/health_stock_surgery/pyproject.toml
trytond/modules/health_stock_surgery/tests/__init__.py
trytond/modules/health_stock_surgery/tests/test_health_stock_surgery.py
trytond/modules/health_stock_surgery/tryton.cfg
trytond/modules/health_stock_surgery/view/create_surgery_stock_move.xml
trytond/modules/health_stock_surgery/view/surgery_form.xml
trytond/modules/health_stock_surgery/wizard/__init__.py
trytond/modules/health_stock_surgery/wizard/create_surgery_stock_move.xml
trytond/modules/health_stock_surgery/wizard/wizard_create_surgery_stock_move.py
gnuhealth_stock_surgery-5.0.2.dist-info/METADATA
gnuhealth_stock_surgery-5.0.2.dist-info/WHEEL
gnuhealth_stock_surgery-5.0.2.dist-info/licenses/COPYING
gnuhealth_stock_surgery-5.0.2.dist-info/RECORD
